nornir_cli/__init__.py
nornir_cli/common_commands/__init__.py
nornir_cli/common_commands/cmd_change_credentials.py
nornir_cli/common_commands/cmd_filter.py
nornir_cli/common_commands/cmd_init.py
nornir_cli/common_commands/cmd_print_result.py
nornir_cli/common_commands/cmd_show_inventory.py
nornir_cli/common_commands/cmd_write_file.py
nornir_cli/common_commands/cmd_write_result.py
nornir_cli/common_commands/cmd_write_results.py
nornir_cli/common_commands/common.py
nornir_cli/common_commands/print_result.py
nornir_cli/common_commands/static_options.py
nornir_cli/common_commands/write_result.py
nornir_cli/common_commands/write_results.py
nornir_cli/custom_commands/__init__.py
nornir_cli/nornir_cli.py
nornir_cli/plugin_commands/__init__.py
nornir_cli/plugin_commands/cmd_common.py
nornir_cli/transform/function.py
nornir_cli-1.3.0.dist-info/LICENSE
nornir_cli-1.3.0.dist-info/METADATA
nornir_cli-1.3.0.dist-info/WHEEL
nornir_cli-1.3.0.dist-info/entry_points.txt
nornir_cli-1.3.0.dist-info/RECORD
