Metadata-Version: 2.1
Name: nornir_cli
Version: 1.3.0
Summary: Nornir CLI
Home-page: https://github.com/timeforplanb123/nornir_cli
License: MIT
Keywords: nornir,click,nornir cli,nornir-plugin
Author: Pavel Shemetov
Author-email: timeforplanb123@gmail.com
Requires-Python: >=3.8,<4.0.0
Classifier: License :: OSI Approved :: MIT License
Classifier: Programming Language :: Python :: 3
Classifier: Programming Language :: Python :: 3.8
Classifier: Programming Language :: Python :: 3.9
Classifier: Programming Language :: Python :: 3.10
Classifier: Programming Language :: Python :: 3.11
Classifier: Programming Language :: Python :: 3.12
Requires-Dist: click (==8.1.7)
Requires-Dist: netmiko (==4.1.2)
Requires-Dist: nornir (==3.4.1)
Requires-Dist: nornir-f5 (==0.6.1)
Requires-Dist: nornir-http (==0.1.3)
Requires-Dist: nornir-jinja2 (==0.2.0)
Requires-Dist: nornir-napalm (==0.4.0)
Requires-Dist: nornir-netbox (==0.3.0)
Requires-Dist: nornir-netconf (==2.0.0)
Requires-Dist: nornir-netmiko (==1.0.0)
Requires-Dist: nornir-paramiko (==0.2.0)
Requires-Dist: nornir-pyez (==0.2.8)
Requires-Dist: nornir-pyxl (==1.0.1)
Requires-Dist: nornir-routeros (==0.6.0)
Requires-Dist: nornir-scrapli (==2023.07.30)
Requires-Dist: nornir-utils (==0.2.0)
Requires-Dist: scrapli (==2023.07.30)
Requires-Dist: scrapli-community (==2023.07.30)
Requires-Dist: scrapli-netconf (==2023.07.30)
Requires-Dist: tqdm (>=4.64.0,<5.0.0)
Requires-Dist: ttp (>=0.9.1,<0.10.0)
Project-URL: Documentation, https://timeforplanb123.github.io/nornir_cli/
Project-URL: Repository, https://github.com/timeforplanb123/nornir_cli
